{
	"motion":
	{
 		"ShowFieldsOnCondition_0":
		{
			"sNote":		["For Hide Invisible"],
			"aField_ID":	["sAddPrintSpisok", "date_today","sResultConclusion",
						 	 "sNameOrgan01","sNameOrgan02","sNameOrgan03","sNameOrgan04","sNameOrgan05","sNameOrgan06","sNameOrgan07","sNameOrgan08","sNameOrgan09",
							 "sAddress01","sAddress02","sAddress03","sAddress04","sAddress05","sAddress06","sAddress07","sAddress08","sAddress09",
							 "sPhoneOrgan01","sPhoneOrgan02","sPhoneOrgan03","sPhoneOrgan04","sPhoneOrgan05","sPhoneOrgan06","sPhoneOrgan07","sPhoneOrgan08","sPhoneOrgan09",
							 "sWorkTime01","sWorkTime02","sWorkTime03","sWorkTime04","sWorkTime05","sWorkTime06","sWorkTime07","sWorkTime08","sWorkTime09",
							 "nFileVidpovid01","nFileVidpovid02","nFileVidpovid03","nFileVidpovid04","nFileVidpovid05","nFileVidpovid06","nFileVidpovid07","nFileVidpovid08","nFileVidpovid09"],
			"asID_Field":	{"sClient":"sID_Public_SubjectOrganJoin"},
			"sCondition":	"[sClient] == 'Not_Correct'"
		},
 		"ShowFieldsOnCondition_1":
		{
			"sNote":		["For Show Viyskomat"],
			"aField_ID":	["nFile_Military_ID"],
			"asID_Field":	{"sClient":"asEnumType_Stat"},
			"sCondition":	"[sClient] == 'sElement_Men'"
		},
		"RequiredFieldsOnCondition_1": 
		{
			"aField_ID":	["nFile_Military_ID"],
			"asID_Field":	{"sClient":"asEnumType_Stat"},
			"sCondition":	"[sClient] == 'sElement_Men'"
		},
 		"ShowFieldsOnCondition_2":
		{
			"sNote":		["For Show Declaration"],
			"aField_ID":	["nFile_Declaration"],
			"asID_Field":	{"sClient":"asEnumType_DneprRegistration"},
			"sCondition":	"[sClient] == 'sElement_InDnepr'"
		},
		"RequiredFieldsOnCondition_2": 
		{
			"aField_ID":	["nFile_Declaration"],
			"asID_Field":	{"sClient":"asEnumType_DneprRegistration"},
			"sCondition":	"[sClient] == 'sElement_InDnepr'"
		},
 		"ShowFieldsOnCondition_3":
		{
			"sNote":		["For Show massage Submit Declaration"],
			"aField_ID":	["sLabel03"],
			"asID_Field":	{"sClient":"asEnumType_DneprRegistration"},
			"sCondition":	"[sClient] == 'sElement_OutDnepr'"
		},
 		"ShowFieldsOnCondition_4":
		{
			"sNote":		["For Show massage NOT Submit Military_ID"],
			"aField_ID":	["sLabel04"],
			"asID_Field":	{"sClient":"asEnumType_Stat"},
			"sCondition":	"[sClient] == 'sElement_Women'"
		}
   	}
}
