{"aField":[
   {"id":"asProtocolType","name":"Який протокол","type":"enum",
    "a":[
      {"id":"sEnumProtocolType_1","name":"Протокол про правопорушення у сфері містобудівної діяльності"},
      {"id":"sEnumProtocolType_2","name":"Протокол про адміністративне правопорушення"}]
   },
   {"id":"sOffense","name":"Правопорушення","type":"textArea"},
   {"id":"asRefEntity","name":"Який протокол","type":"enum",
    "a":[
      {"id":"sEnumCompany","name":"юридична особа"},
      {"id":"sEnumIndividual","name":"фізична особа"}]
   },
   {"id":"sPibResp","name":"ПІБ особи, яка притягається до відповідальності","type":"string"},
   {"id":"sDateOfBirthResp","name":"Місце складання припису","type":"date"},
   {"id":"sPlaceOfBirthResp","name":"Місце народження","type":"string"},
   {"id":"sPlaceOfLiveResp","name":"Місце проживання","type":"string"},
   {"id":"sPlaceOfWorkResp","name":"Місце роботи (навчання)","type":"string"},
   {"id":"sPositionResp","name":"Посада","type":"string"},
   {"id":"sIdentityResp","name":"Документ, що посвідчує особу","type":"string"},
   {"id":"sTaxNumberResp","name":"ІПН","type":"string"},
   {"id":"sNameCompany","name":"Найменування юридичної особи","type":"string"},
   {"id":"sAddressCompany","name":"Місцезнаходження юридичної особи","type":"string"},
   {"id":"sInnCompany","name":"Код за ЄДРПОУ","type":"string"},
   {"id":"sChiefPib","name":"Посада та ПІБ керівника","type":"string"},
   {"id":"sOtherInformationResp","name":"Інші відомості","type":"string"},

   {"id":"sContractorName","name":"Будівельна організація","type":"string"},   
   {"id":"sSupervisionPib","name":"Технічний нагляд","type":"string"},
   {"id":"sProjectName","name":"Проектна організація","type":"string"},
   {"id":"sArchitectPib","name":"Авторський нагляд","type":"string"},
   {"id":"sExpertName","name":"Експертна організація","type":"string"},

   {"id":"sArticleResponsibility","name":"Стаття відповідальності","type":"string"},
   {"id":"sDateCase","name":"Дата та час розгляду справи","type":"string"},
   {"id":"sPlaceCase","name":"Місце розгляду справи","type":"string"},
   {"id":"sAddressPlaceCase","name":"Адреса місця розгляду справи","type":"string"},

   {"id":"sDocumentCase","name":"Документи, які складені за результатами перевірки","type":"textArea"},
   {"id":"sOffensesResolution","name":"Порушення","type":"textArea"},
   {"id":"sPersonsControl","name":"Особи, які брали участь у розгляді справи","type":"textArea"},
   {"id":"sFine","name":"Штраф у розмірі","type":"string"},
   {"id":"sPaymentDetails","name":"Реквізити для оплати","type":"string"},
   {"id":"sDecidedControl","name":"Установив","type":"string"}
]}