{
	"motion": 
	{
		"ShowElementsOnTrue_21": 
		{
			"aElement_ID":	["UR","UR_sLocation","UR_inn","FIO_UR"],
			"asID_Field":	{"sClient":"asOsoba"},
			"sCondition":	"[sClient] == 'sEnamUrK' || [sClient] == 'sEnamUrP'"
		},
		"ShowElementsOnTrue_22": 
		{
			"aElement_ID":	["FOP","FOP_sLocation","FOP_inn","FIO_FOP"],
			"asID_Field":	{"sClient":"asOsoba"},
			"sCondition":	"[sClient] == 'sEnamFOP'"
		},
		"ShowElementsOnTrue_23": 
		{
			"aElement_ID":	["Other_phone"],
			"asID_Field":	{"sClient":"sOtherPhone"},
			"sCondition":	"[sClient] != '' && [sClient] != ' '"
		},
		"ShowElementsOnTrue_24": 
		{
			"aElement_ID":	["City_phone"],
			"asID_Field":	{"sClient":"sMisPhone"},
			"sCondition":	"[sClient] != '' && [sClient] != ' '"
		},
		"ShowElementsOnTrue_25": 
		{
			"aElement_ID":	["Org3_1","Org3_2","Org3_3","Org3_4"],
			"asID_Field":	{"sClient":"asAddCulture"},
			"sCondition":	"[sClient] == 'yes'"
		},
		"ShowElementsOnTrue_26": 
		{
			"aElement_ID":	["Org4_1","Org4_2","Org4_3","Org4_4"],
			"asID_Field":	{"sClient":"asAddCulture"},
			"sCondition":	"[sClient] != 'yes'"
		}
	}
}