{
  "motion": {
    "ValuesFieldsOnCondition_14": {
      "aField_ID": [
        "servitut_pr",
        "ipoteka_pr",
        "volodinya_pr",
        "dovira_pr",
        "orenda_pr",
        "vidanya_pr",
        "upravlinya_pr",
        "zabudova_pr",
        "postiine_pr",
        "selo_pr",
        "korystuvanya_pr",
        "inshe_pr"
      ],
      "asID_Field_sValue": [
        " ",
        " ",
        " ",
        " ",
        " ",
        " ",
        " ",
        " ",
        " ",
        " ",
        "&#10004;",
        " "
      ],
      "asID_Field": {
        "sReason": "rechove_pravo"
      },
      "sCondition": "[sReason] == 'korystuvanya'"
    },
    "ValuesFieldsOnCondition_15": {
      "aField_ID": [
        "servitut_pr",
        "ipoteka_pr",
        "volodinya_pr",
        "dovira_pr",
        "orenda_pr",
        "vidanya_pr",
        "upravlinya_pr",
        "zabudova_pr",
        "postiine_pr",
        "selo_pr",
        "korystuvanya_pr",
        "inshe_pr"
      ],
      "asID_Field_sValue": [
        " ",
        " ",
        " ",
        " ",
        " ",
        " ",
        " ",
        " ",
        " ",
        " ",
        " ",
        "&#10004;"
      ],
      "asID_Field": {
        "sReason": "rechove_pravo"
      },
      "sCondition": "[sReason] == 'inshe'"
    },
    "ValuesFieldsOnCondition_16": {
      "aField_ID": [
        "dilyanka_pr",
        "nezhytlove_pr",
        "zhytlove_pr",
        "kvartyra_pr",
        "nezav_budiv_pr",
        "zhytl_budynok_pr",
        "budivlya_pr",
        "sporuda_pr"
      ],
      "asID_Field_sValue": [
        "&#10004;",
        " ",
        " ",
        " ",
        " ",
        " ",
        " ",
        " "
      ],
      "asID_Field": {
        "sReason": "type_object"
      },
      "sCondition": "[sReason] == 'dilyanka'"
    },
    "ValuesFieldsOnCondition_17": {
      "aField_ID": [
        "dilyanka_pr",
        "nezhytlove_pr",
        "zhytlove_pr",
        "kvartyra_pr",
        "nezav_budiv_pr",
        "zhytl_budynok_pr",
        "budivlya_pr",
        "sporuda_pr"
      ],
      "asID_Field_sValue": [
        " ",
        "&#10004;",
        " ",
        " ",
        " ",
        " ",
        " ",
        " "
      ],
      "asID_Field": {
        "sReason": "type_object"
      },
      "sCondition": "[sReason] == 'nezhytlove'"
    },
    "ValuesFieldsOnCondition_18": {
      "aField_ID": [
        "dilyanka_pr",
        "nezhytlove_pr",
        "zhytlove_pr",
        "kvartyra_pr",
        "nezav_budiv_pr",
        "zhytl_budynok_pr",
        "budivlya_pr",
        "sporuda_pr"
      ],
      "asID_Field_sValue": [
        " ",
        " ",
        "&#10004;",
        " ",
        " ",
        " ",
        " ",
        " "
      ],
      "asID_Field": {
        "sReason": "type_object"
      },
      "sCondition": "[sReason] == 'zhytlove'"
    },
    "ValuesFieldsOnCondition_19": {
      "aField_ID": [
        "dilyanka_pr",
        "nezhytlove_pr",
        "zhytlove_pr",
        "kvartyra_pr",
        "nezav_budiv_pr",
        "zhytl_budynok_pr",
        "budivlya_pr",
        "sporuda_pr"
      ],
      "asID_Field_sValue": [
        " ",
        " ",
        " ",
        "&#10004;",
        " ",
        " ",
        " ",
        " "
      ],
      "asID_Field": {
        "sReason": "type_object"
      },
      "sCondition": "[sReason] == 'kvartyra'"
    },
    "ValuesFieldsOnCondition_20": {
      "aField_ID": [
        "dilyanka_pr",
        "nezhytlove_pr",
        "zhytlove_pr",
        "kvartyra_pr",
        "nezav_budiv_pr",
        "zhytl_budynok_pr",
        "budivlya_pr",
        "sporuda_pr"
      ],
      "asID_Field_sValue": [
        " ",
        " ",
        " ",
        " ",
        "&#10004;",
        " ",
        " ",
        " "
      ],
      "asID_Field": {
        "sReason": "type_object"
      },
      "sCondition": "[sReason] == 'nezav_budiv'"
    }
  }
}