{  
	"motion": 
	{
  	   "ShowFieldsOnCondition_0":
  	   {
        "aField_ID": ["sFullName_SubjectOrgan_appl", "sShortName_SubjectOrgan_appl","sID_SubjectActionKVED_SubjectOrgan_appl", "sNote_ID_SubjectActionKVED_SubjectOrgan_appl", "sDateActual_SubjectOrgan_appl", "sLocation_SubjectOrgan_appl", "ur_tel", "ur_fax","sID_SubjectOrgan_OKPO_appl","sCEOName_SubjectOrgan_appl","ur_post"],
        "asID_Field": { "sClient": "subekt" },
        "sCondition": "[sClient] == 'ur'"
       },      
       "ShowFieldsOnCondition_00":
       {
        "aField_ID": ["fiz_name","fiz_adres","fiz_drfo"],
        "asID_Field": {"sClient": "subekt"},
        "sCondition": "[sClient] == 'fiz'"
       },
       "ShowFieldsOnCondition_1":
       {
         "aField_ID": ["sID_SubjectOrgan_OKPO_producer","sFullName_SubjectOrgan_producer","sShortName_SubjectOrgan_producer","sID_SubjectActionKVED_SubjectOrgan_producer","sNote_ID_SubjectActionKVED_SubjectOrgan_producer","sLocation_SubjectOrgan_producer","sDateActual_SubjectOrgan_producer"],
         "asID_Field": { "sClient": "subekt_1"},
         "sCondition": "[sClient] == 'ur_1'"
       },
       
       "ShowFieldsOnCondition_11":
       {
         "aField_ID": ["fiz_name_1","fiz_adres_1" ],
         "asID_Field": {"sClient": "subekt_1"},
         "sCondition": "[sClient] == 'fiz_1'"
       },
       
       "ShowFieldsOnCondition_2":
       {
         "aField_ID": ["sID_SubjectOrgan_OKPO_buyer","sFullName_SubjectOrgan_buyer","sShortName_SubjectOrgan_buyer","sID_SubjectActionKVED_SubjectOrgan_buyer","sNote_ID_SubjectActionKVED_SubjectOrgan_buyer","sLocation_SubjectOrgan_buyer","sDateActual_SubjectOrgan_buyer"],
         "asID_Field": { "sClient": "subekt_2" },
         "sCondition": "[sClient] == 'ur_2'"
       },       
       "ShowFieldsOnCondition_22":
       {
         "aField_ID": ["fiz_name_2", "fiz_adres_2" ],
         "asID_Field": {"sClient": "subekt_2"},
         "sCondition": "[sClient] == 'fiz_2'"
       },       
       "ShowFieldsOnCondition_16":
       {
         "aField_ID": [ "basis_1" ],
         "asID_Field": { "sClient": "basis"},
         "sCondition": "[sClient] == 'exw'"
       },       
       "ShowFieldsOnCondition_17":
       {
         "aField_ID": ["basis_2"],
         "asID_Field": {"sClient": "basis"},
         "sCondition": "[sClient] == 'fса'||[sClient] == 'срт'||[sClient] == 'сір'||[sClient] == 'ddu'||[sClient] == 'ddр'"
       },       
       "ShowFieldsOnCondition_18":
       {
         "aField_ID": [ "basis_3" ],
         "asID_Field": { "sClient": "basis" },
         "sCondition": "[sClient] == 'fаs'||[sClient] == 'fов'"
       },       
       "ShowFieldsOnCondition_19":
       {
         "aField_ID": ["basis_4" ],
         "asID_Field": {"sClient": "basis"},
         "sCondition": "[sClient] == 'сfr'||[sClient] == 'сіf'||[sClient] == 'dеs'||[sClient] == 'dеq'"
       },       
       "ShowFieldsOnCondition_20":
       {
         "aField_ID": ["basis_5"],
         "asID_Field": {"sClient": "basis"},
         "sCondition": "[sClient] == 'dаf'"
        }   
  	}
}