{
  "motion": {
    "RequiredFieldsOnCondition_1": 
    {
      "aField_ID": ["comment_1"],
      "asID_Field": 
      {
        "sClient": "decision_1"
      },
      "sCondition": "[sClient]=='reject'"
    },
    "RequiredFieldsOnCondition_2": 
    {
      "aField_ID": ["comment_2"],
      "asID_Field": 
      {
        "sClient1": "decision_2"
      },
      "sCondition": "[sClient1]=='reject'"
    },
    "RequiredFieldsOnCondition_3": 
    {
      "aField_ID": ["comment"],
      "asID_Field": 
      {
        "sClient2": "decide"
      },
      "sCondition": "[sClient2]=='reject'"
    }
  }
}