{
  "motion": {
    "ShowFieldsOnCondition_1": {
      "aField_ID": [
        "sSubzvern",
        "sEdrpou"
      ],
      "asID_Field": {
        "sZnach": "asOsoba"
      },
      "sCondition": "[sZnach] == 'sEnamUr'"
    },
    "ShowFieldsOnCondition_2": {
      "aField_ID": [
        "bankIdPassport",
        "bankIdinn"
      ],
      "asID_Field": {
        "sZnach": "asOsoba"
      },
      "sCondition": "[sZnach] == 'sEnamFiz'"
    },
    "ShowFieldsOnCondition_3": {
      "aField_ID": [
        "sLicenz",
        "asLicenzChange"
      ],
      "asID_Field": {
        "sZnach": "asLicenz"
      },
      "sCondition": "[sZnach] == 'sEnamLic_old'"
    },
    "ShowFieldsOnCondition_4": {
      "aField_ID": [
        "file_lic_change",
        "sLicenz_zmina"
      ],
      "asID_Field": {
        "sZnach": "asLicenz", "sZnach2": "asLicenzChange" 
      },
      "sCondition": "[sZnach] == 'sEnamLic_old'&&[sZnach2] == 'sEnamLic_Change'"
    }
  }
}