{	

	"motion":
	{
		"ShowFieldsOnCondition_1":
		{
			"aField_ID": ["sNameUr","sPosada"],
			"asID_Field":
			{
				"sClient": "sSubekt" 
			},
			"sCondition":"[sClient]=='ur'||[sClient]=='юридична особа'" 
		},
		"ShowFieldsOnCondition_2":
		{
			"aField_ID": ["sNameUnion","sPosada"],
			"asID_Field":
			{
				"sClient1":"sSubekt"
			},
			"sCondition":"[sClient1]=='union'"
		}
		
	},
	"validate": 
	{
    	"CustomFormat_1": 
    	{
      		"aField_ID": ["sIndex"],
      		"sFormat": "#####",
      		"sMessage": "Невірний формат індексу, введіть індекс у форматі #####" 
    }
  }
}